{"hash": "c95501ce59cd87e520697dcd875f75cc412e58cf", "message": "Fixed Eclipse project.\nPush4Bitwig\n* New: Support for pinning tracks and devices\n* New: Harmonized track navigation with master track. Pressing the button below the master track will move into the master tracks' devices. Going up from devices selects the master track.\nAPC4Bitwig\n* New: Display the view names when switching between them.\nMCU4Bitwig\n* New: Option to deactivate the automatic selection of track when the channel fader is touched.", "file_num_lines": 522, "diff_parsed": {"added": [[93, "        if (l == null)"], [94, "            return;"], [305, "        final Display d = this.surface.getDisplay ().clear ();"], [309, "            d.setBlock (1, 0, \"           Select\").setBlock (1, 1, \"a device or press\").setBlock (1, 2, \"'Add Effect'...  \").allDone ();"], [313, "        final boolean noLayers = cd.hasLayers () && cd.hasZeroLayers ();"], [314, "        if (noLayers)"], [316, "            d.setBlock (1, 1, \"    Please create\").setBlock (1, 2, cd.hasDrumPads () ? \"a Drum Pad...\" : \"a Device Layer...\");"], [320, "            final ChannelData l = cd.getSelectedLayerOrDrumPad ();"], [321, "            if (l != null)"], [323, "                d.setCell (0, 0, \"Volume\").setCell (1, 0, l.getVolumeStr (8)).setCell (2, 0, this.surface.getConfiguration ().isEnableVUMeters () ? l.getVu () : l.getVolume (), Format.FORMAT_VALUE);"], [324, "                d.setCell (0, 1, \"Pan\").setCell (1, 1, l.getPanStr (8)).setCell (2, 1, l.getPan (), Format.FORMAT_PAN);"], [325, ""], [326, "                final EffectTrackBankProxy fxTrackBank = this.model.getEffectTrackBank ();"], [327, "                if (fxTrackBank == null)"], [329, "                    for (int i = 0; i < 6; i++)"], [331, "                        final int pos = 2 + i;"], [332, "                        final SendData sendData = l.getSends ()[i];"], [333, "                        d.setCell (0, pos, sendData.getName ()).setCell (1, pos, sendData.getDisplayedValue (8)).setCell (2, pos, sendData.getValue (), Format.FORMAT_VALUE);"], [335, "                }"], [336, "                else"], [337, "                {"], [338, "                    final boolean isFX = this.model.isEffectTrackBankActive ();"], [339, "                    for (int i = 0; i < 6; i++)"], [341, "                        final TrackData fxTrack = fxTrackBank.getTrack (i);"], [342, "                        final boolean isEmpty = isFX || !fxTrack.doesExist ();"], [343, "                        final int pos = 2 + i;"], [344, "                        if (isEmpty)"], [345, "                        {"], [346, "                            d.clearCell (0, pos);"], [347, "                            d.clearCell (2, pos);"], [348, "                        }"], [349, "                        else"], [350, "                        {"], [351, "                            d.setCell (0, pos, fxTrack.getName ()).setCell (1, pos, l.getSends ()[i].getDisplayedValue (8));"], [352, "                            d.setCell (2, pos, l.getSends ()[i].getValue (), Format.FORMAT_VALUE);"], [353, "                        }"], [371, "            for (int i = 0; i < 8; i++)"], [372, "                message.addOptionElement (i == 2 ? \"Please select a device or press 'Add Device'...\" : \"\", i == 7 ? \"Up\" : \"\", true, \"\", \"\", false, true);"], [373, "            message.send ();"], [377, "        final boolean noLayers = cd.hasLayers () && cd.hasZeroLayers ();"], [378, "        if (noLayers)"], [380, "            for (int i = 0; i < 8; i++)"], [381, "                message.addOptionElement (i == 3 ? \"Please create a \" + (cd.hasDrumPads () ? \"Drum Pad...\" : \"Device Layer...\") : \"\", i == 7 ? \"Up\" : \"\", true, \"\", \"\", false, true);"], [382, "            message.send ();"], [387, "        this.updateDisplayElements (message, cd, cd.getSelectedLayerOrDrumPad ());"], [596, "            this.surface.updateButton (109, this.isPush2 ? PushColors.PUSH2_COLOR2_WHITE : PushColors.PUSH1_COLOR2_WHITE);"]], "deleted": [[303, "        final Display d = this.surface.getDisplay ();"], [307, "            d.clear ().setBlock (1, 0, \"           Select\").setBlock (1, 1, \"a device or press\").setBlock (1, 2, \"'Add Effect'...  \").allDone ();"], [311, "        d.clear ();"], [312, ""], [313, "        final ChannelData l = cd.getSelectedLayerOrDrumPad ();"], [314, "        if (l == null)"], [316, "            final boolean noLayers = cd.hasLayers () && cd.hasZeroLayers ();"], [317, "            d.setBlock (1, 1, \"    Please \" + (noLayers ? \"create\" : \"select\")).setBlock (1, 2, cd.hasDrumPads () ? \"a Drum Pad...\" : \"a Device Layer...\");"], [321, "            d.setCell (0, 0, \"Volume\").setCell (1, 0, l.getVolumeStr (8)).setCell (2, 0, this.surface.getConfiguration ().isEnableVUMeters () ? l.getVu () : l.getVolume (), Format.FORMAT_VALUE);"], [322, "            d.setCell (0, 1, \"Pan\").setCell (1, 1, l.getPanStr (8)).setCell (2, 1, l.getPan (), Format.FORMAT_PAN);"], [323, ""], [324, "            final EffectTrackBankProxy fxTrackBank = this.model.getEffectTrackBank ();"], [325, "            if (fxTrackBank == null)"], [327, "                for (int i = 0; i < 6; i++)"], [328, "                {"], [329, "                    final int pos = 2 + i;"], [330, "                    final SendData sendData = l.getSends ()[i];"], [331, "                    d.setCell (0, pos, sendData.getName ()).setCell (1, pos, sendData.getDisplayedValue (8)).setCell (2, pos, sendData.getValue (), Format.FORMAT_VALUE);"], [332, "                }"], [333, "            }"], [334, "            else"], [335, "            {"], [336, "                final boolean isFX = this.model.isEffectTrackBankActive ();"], [337, "                for (int i = 0; i < 6; i++)"], [339, "                    final TrackData fxTrack = fxTrackBank.getTrack (i);"], [340, "                    final boolean isEmpty = isFX || !fxTrack.doesExist ();"], [341, "                    final int pos = 2 + i;"], [342, "                    if (isEmpty)"], [344, "                        d.clearCell (0, pos);"], [345, "                        d.clearCell (2, pos);"], [347, "                    else"], [349, "                        d.setCell (0, pos, fxTrack.getName ()).setCell (1, pos, l.getSends ()[i].getDisplayedValue (8));"], [350, "                        d.setCell (2, pos, l.getSends ()[i].getValue (), Format.FORMAT_VALUE);"], [368, "            message.setMessage (3, \"Please select a device or press 'Add Device'...\").send ();"], [372, "        final ChannelData l = cd.getSelectedLayerOrDrumPad ();"], [373, "        if (l == null)"], [375, "            final boolean noLayers = cd.hasLayers () && cd.hasZeroLayers ();"], [376, "            message.setMessage (2, \"Please \" + (noLayers ? \"create\" : \"select\") + \" a \" + (cd.hasDrumPads () ? \"Drum Pad...\" : \"Device Layer...\")).send ();"], [381, "        this.updateDisplayElements (message, cd, l);"]]}, "num_lines_added": 46, "num_lines_removed": 39}