{"hash": "afcb9ab7c44afd075097c65a7f9122155df6e724", "message": "Fix NPE for docker:logs (#612)\n\nFixes #612.\n\nSigned-off-by: Roland Hu\u00df <roland@ro14nd.de>", "file_num_lines": 62, "diff_parsed": {"added": [[55, "                if (container != null) {"], [56, "                    doLogging(logDispatcher, image, container.getId());"], [57, "                }"]], "deleted": [[55, "                doLogging(logDispatcher, image, container.getId());"]]}, "num_lines_added": 3, "num_lines_removed": 1}