{
    "bug_type": "DOTNET_RESOURCE_LEAK",
    "qualifier": "Leaked resource this.NetMQ.zmq.Signaler.m_w of type System.Net.Sockets.Socket, Leaked resource sync of type System.Threading.Mutex in method \"Void Signaler.MakeFDpair()\".",
    "severity": "ERROR",
    "line": 74,
    "column": 3,
    "procedure": "Void Signaler.MakeFDpair()",
    "procedure_start_line": 74,
    "file": "src/NetMQ/zmq/Signaler.cs",
    "bug_trace": [],
    "key": "Signaler.cs|MakeFDpair|DOTNET_RESOURCE_LEAK",
    "hash": "f7bc7dabf0bf262775b0a7426cd4d4a6",
    "bug_type_hum": "Dotnet Resource Leak"
}