{
    "bug_type": "DOTNET_RESOURCE_LEAK",
    "qualifier": "Leaked resource (output of System.Net.Http.HttpClient::.ctor() at Line 73) of type System.Net.Http.HttpClient in method \"Void ViewClientTests.When_Url_Is_Invalid_WebException_Is_Returned()\".",
    "severity": "ERROR",
    "line": 67,
    "column": 9,
    "procedure": "Void ViewClientTests.When_Url_Is_Invalid_WebException_Is_Returned()",
    "procedure_start_line": 67,
    "file": "Src/Couchbase.Tests/Views/ViewClientTests.cs",
    "bug_trace": [],
    "key": "ViewClientTests.cs|When_Url_Is_Invalid_WebException_Is_Returned|DOTNET_RESOURCE_LEAK",
    "hash": "8c349fd750339ef30ef766b2f2bf749f",
    "bug_type_hum": "Dotnet Resource Leak"
}