{
    "hash": "e90a3232bdecf003e61bd55bd06c77566cfb00df",
    "message": "Upgrade the samples to 8.8.0",
    "file_num_lines": 142,
    "diff_parsed": {
        "added": [
            [
                50,
                "        private static readonly string ETextSampleInput = @\""
            ],
            [
                51,
                "SEVERE [MBT Director for SESS_0.8396720957269632] TCP should be ready, begin recreate IO Socket"
            ],
            [
                52,
                "INFO [MBT Director for SESS_0.8396720957269632] SendTCPMessage: Sending - performGeneralAction`StartApplication`calc``"
            ],
            [
                53,
                "INFO [MBT Director for SESS_0.8396720957269632] SendTCPMessage: Received - -1"
            ],
            [
                54,
                "SEVERE [MBT Director for SESS_0.8396720957269632] performGeneralAction(): return code is ERROR - unknown. An exception may have occurred."
            ],
            [
                55,
                "INFO [vUser-3-thread-1] SendTCPMessage: Sending - findElement`Clear`true`name`button`1`false`0`true"
            ],
            [
                56,
                "INFO [vUser-3-thread-1] SendTCPMessage: Received - 1"
            ],
            [
                57,
                "INFO [vUser-3-thread-1] findElement(): return code is FAILED\";"
            ],
            [
                58,
                ""
            ],
            [
                142,
                ""
            ],
            [
                143,
                "            // IV. Learn EText program"
            ],
            [
                144,
                "            session.Inputs.Clear();"
            ],
            [
                145,
                "            session.Constraints.Clear();"
            ],
            [
                146,
                "            session.AddInput(ETextSampleInput);"
            ],
            [
                147,
                "            // EText learning is disabled by default while we work to improve its quality."
            ],
            [
                148,
                "            session.Constraints.Add(EnableExtractionTextLearning.Instance);"
            ],
            [
                149,
                "            Program prog4 = session.Learn();"
            ],
            [
                150,
                "            PrintProgramProperties(prog4);"
            ],
            [
                151,
                "            PrintProgramOutput(prog4, ETextSampleInput);"
            ]
        ],
        "deleted": []
    },
    "num_lines_added": 19,
    "num_lines_removed": 0
}