{"bug_class": "PROVER", "kind": "ERROR", "bug_type": "THREAD_SAFETY_VIOLATION", "qualifier": "Read/Write race. Non-private method `com.hannesdorfmann.fragmentargs.processor.ArgProcessor.process` reads without synchronization from `this.com.hannesdorfmann.fragmentargs.processor.ArgProcessor.TYPE_FRAGMENT`. Potentially races with write in method `ArgProcessor.init(...)`.\n Reporting because another access to the same memory occurs on a background thread, although this access may not.", "severity": "HIGH", "visibility": "user", "line": 503, "column": -1, "procedure": "boolean ArgProcessor.process(Set,RoundEnvironment)", "procedure_id": "com.hannesdorfmann.fragmentargs.processor.ArgProcessor.process(java.util.Set,javax.annotation.proces.64c10516612da3b6ec96ee3e5709c45c", "procedure_start_line": 458, "file": "processor/src/main/java/com/hannesdorfmann/fragmentargs/processor/ArgProcessor.java", "bug_trace": [{"level": 0, "filename": "processor/src/main/java/com/hannesdorfmann/fragmentargs/processor/ArgProcessor.java", "line_number": 503, "column_number": -1, "description": "<Read trace>"}, {"level": 0, "filename": "processor/src/main/java/com/hannesdorfmann/fragmentargs/processor/ArgProcessor.java", "line_number": 503, "column_number": -1, "description": "access to `this.com.hannesdorfmann.fragmentargs.processor.ArgProcessor.TYPE_FRAGMENT`"}, {"level": 0, "filename": "processor/src/main/java/com/hannesdorfmann/fragmentargs/processor/ArgProcessor.java", "line_number": 131, "column_number": -1, "description": "<Write trace>"}, {"level": 0, "filename": "processor/src/main/java/com/hannesdorfmann/fragmentargs/processor/ArgProcessor.java", "line_number": 131, "column_number": -1, "description": "access to `this.com.hannesdorfmann.fragmentargs.processor.ArgProcessor.TYPE_FRAGMENT`"}], "key": "ArgProcessor.java|process|THREAD_SAFETY_VIOLATION", "node_key": "9c5d6d9028928346cc4fb44cced5dea1", "hash": "6b0c7bcde683e8ac1764e42feaa9945f", "bug_type_hum": "Thread Safety Violation", "censored_reason": ""}