{
    "bug_type": "DOTNET_RESOURCE_LEAK",
    "qualifier": "Leaked resource content of type System.Net.Http.StringContent in method \"Void HalResourceMixedContentTest.peopledetail_get_xml_test()\".",
    "severity": "ERROR",
    "line": 56,
    "column": 9,
    "procedure": "Void HalResourceMixedContentTest.peopledetail_get_xml_test()",
    "procedure_start_line": 56,
    "file": "WebApi.Hal.Tests/HalResourceMixedContentTest.cs",
    "bug_trace": [],
    "key": "HalResourceMixedContentTest.cs|peopledetail_get_xml_test|DOTNET_RESOURCE_LEAK",
    "hash": "6208208c34d33061961813751d7cbea3",
    "bug_type_hum": "Dotnet Resource Leak"
}