{
    "hash": "20cf6fd0265eb956498cacbb07bd5a95e7f4b9bd",
    "message": "Redefine articulation points so they work more sensibly with relevant.",
    "file_num_lines": 200,
    "diff_parsed": {
        "added": [
            [
                178,
                "            var seed = Environment.TickCount;"
            ],
            [
                179,
                "            var r = new Random(seed);"
            ],
            [
                180,
                "            Console.WriteLine(\"Seed {0}\", seed);"
            ],
            [
                181,
                ""
            ],
            [
                194,
                "            var propagator = new TilePropagator(model, topology, new TilePropagatorOptions"
            ],
            [
                195,
                "            {"
            ],
            [
                196,
                "                RandomDouble = r.NextDouble,"
            ],
            [
                197,
                "                Constraints = new[] { constraint }"
            ],
            [
                198,
                "            });"
            ]
        ],
        "deleted": [
            [
                190,
                "            var propagator = new TilePropagator(model, topology, constraints: new[] { constraint });"
            ]
        ]
    },
    "num_lines_added": 9,
    "num_lines_removed": 1
}