{"hash": "c78daadf86492abb1e6dacb822bb6474a397067d", "message": "Added plan status verification and pattern matching to path", "file_num_lines": 160, "diff_parsed": {"added": [[26, "import br.com.conductor.heimdall.core.enums.Status;"], [28, "import br.com.conductor.heimdall.core.repository.PlanRepository;"], [49, "    @Autowired"], [50, "    private PlanRepository planRepository;"], [51, ""], [101, "        final Plan plan1 = planRepository.findOne(referenceId);"], [102, "        if (plan1 != null)"], [103, "            if (!Status.ACTIVE.equals(plan1.getStatus()))"], [104, "                return false;"], [105, ""], [131, "                if (pathMatcher.match(req.getRequestURI(), path)) return true;"]], "deleted": [[121, "                if (req.getRequestURI().contains(path)) return true;"]]}, "num_lines_added": 11, "num_lines_removed": 1}