{
    "hash": "a68291e9a5041416f74dfe71d0c1a3fcf4a39ef4",
    "message": "\u83b7\u53d6 index",
    "file_num_lines": 102,
    "diff_parsed": {
        "added": [
            [
                52,
                "                int index =reader.GetOrdinal(\"cdata\");"
            ],
            [
                53,
                "                Console.WriteLine($\"cdata index at {index}\");"
            ]
        ],
        "deleted": []
    },
    "num_lines_added": 2,
    "num_lines_removed": 0
}