{"hash": "08b4bd88324ae809f204d37cc9c286a0ff736b3b", "message": "Refactoring class AlgorithmAttributes and NSGAIIAttr", "file_num_lines": 28, "diff_parsed": {"added": [[25, "import org.uma.jmetal3.metaheuristic.multiobjective.nsgaii.NSGAIIAttr;"], [62, "    double distance1 = NSGAIIAttr.getAttributes(o1).getCrowdingDistance() ;"], [63, "    double distance2 = NSGAIIAttr.getAttributes(o2).getCrowdingDistance() ;"], [64, "    //double distance1 = (double)o1.getAlgorithmAttributes().getAttribute(\"CrowdingDistance\");"], [65, "    //double distance2 = (double)o2.getAlgorithmAttributes().getAttribute(\"CrowdingDistance\");"]], "deleted": [[61, "    double distance1 = (double)o1.getAlgorithmAttributes().getAttribute(\"CrowdingDistance\");"], [62, "    double distance2 = (double)o2.getAlgorithmAttributes().getAttribute(\"CrowdingDistance\");"]]}, "num_lines_added": 5, "num_lines_removed": 2}