{"hash": "9ded30c1ad91af852c9f56bf79b37422aca0712c", "message": "Fixed ui, controller, and partition_assigner for partition balancing", "file_num_lines": 83, "diff_parsed": {"added": [[32, ""], [33, "    for (Host host : ring.getHosts()) {"], [34, "      if (host.getDomainById(domainId) == null)"], [35, "        host.addDomain(domainId);"], [36, "    }"], [76, "    int maxDistance = Math.abs(maxHostDomain.getPartitions().size() - minHostDomain.getPartitions().size());"]], "deleted": [[71, "    int maxDistance = Math.abs(maxHostDomain.getPartitions().size()"], [72, "        - minHostDomain.getPartitions().size());"]]}, "num_lines_added": 6, "num_lines_removed": 2}