{"hash": "6154a3100a0a56d75ebbee49d15bfc8a2bca3249", "message": "Fix #166: Don't block deployment when @Eager @ApplicationScoped fails.\nTook opportunity to only register EagerBeansWebListener when necessary.", "file_num_lines": 74, "diff_parsed": {"added": [[19, "import javax.servlet.ServletContext;"], [25, "import org.omnifaces.cdi.eager.EagerBeansWebListener;"], [39, " * <li>Instantiate {@link Eager} application scoped beans and register its {@link EagerBeansWebListener} if necessary."], [61, "\t\t\tServletContext servletContext = event.getServletContext();"], [62, "\t\t\tEagerBeansRepository.instantiateApplicationScopedAndRegisterListener(servletContext);"], [63, "\t\t\tFacesViews.addMappings(servletContext);"], [64, "\t\t\tCacheInitializer.loadProviderAndRegisterFilter(servletContext);"]], "deleted": [[37, " * <li>Instantiate {@link Eager} application scoped beans."], [59, "\t\t\tEagerBeansRepository.getInstance().instantiateApplicationScoped();"], [60, "\t\t\tFacesViews.addMappings(event.getServletContext());"], [61, "\t\t\tCacheInitializer.loadProviderAndRegisterFilter(event.getServletContext());"], [107, ""]]}, "num_lines_added": 7, "num_lines_removed": 5}